libify/__init__.py
libify-0.78.dist-info/LICENSE
libify-0.78.dist-info/METADATA
libify-0.78.dist-info/WHEEL
libify-0.78.dist-info/top_level.txt
libify-0.78.dist-info/RECORD
