Metadata-Version: 2.1
Name: libify
Version: 0.78
Summary: Import Databricks notebooks as libraries/modules
Home-page: https://github.com/vagrantism/libify
Author: Madhup Sukoon
Author-email: 29144316+vagrantism@users.noreply.github.com
License: MIT
Platform: UNKNOWN
Classifier: Programming Language :: Python :: 3
Classifier: License :: OSI Approved :: MIT License
Classifier: Operating System :: OS Independent
Requires-Python: >=3.5
